{
  "messages": [
    {
      "chat_index": "phase_chat",
      "role_name": "user",
      "role_type": "user",
      "role_prompt": "",
      "input_query": "确认本地是否存在employee_data.csv，并查看它有哪些列和数据类型;然后画柱状图",
      "role_content": "确认本地是否存在employee_data.csv，并查看它有哪些列和数据类型;然后画柱状图",
      "step_content": "",
      "parsed_output": {},
      "spec_parsed_output": {},
      "parsed_output_list": [],
      "task": null,
      "db_docs": [],
      "code_docs": [],
      "search_docs": [],
      "customed_kargs": {},
      "phase_name": null,
      "chain_name": null
    },
    {
      "chat_index": "phase_chat",
      "role_name": "code_reacter",
      "role_type": "assistant",
      "role_prompt": "",
      "input_query": "确认本地是否存在employee_data.csv，并查看它有哪些列和数据类型;然后画柱状图",
      "role_content": "\n**Thoughts:**\nThe file \"employee_data.csv\" exists and contains 5 columns with different data types. Now, we need to create a bar chart.\n**Action Status:**\ncode_executing\n**Action:**\n```python\n# Create a bar chart\nimport matplotlib.pyplot as plt\n\n# Count the number of employees in each department\ndepartment_counts = data['Department'].value_counts()\n\n# Plot the bar chart\ndepartment_counts.plot(kind='bar')\nplt.title('Number of Employees in Each Department')\nplt.xlabel('Department')\nplt.ylabel('Number of Employees')\nplt.show()\n```\n",
      "step_content": "\n\n**Thoughts:** The user needs to confirm the existence of the \"employee_data.csv\" file, check its columns and data types, and then create a bar chart.\n\n**Action Status:** code_executing\n\n**Action:** \n```python\n# Check if the file \"employee_data.csv\" exists\nimport os\nfile_exists = os.path.isfile('employee_data.csv')\nfile_exists\n```\n\n\n**Observation:**: The return information after executing the above code is True\n.\n\n\n\n**Thoughts:**\nThe file \"employee_data.csv\" exists, so now we need to check its columns and data types.\n**Action Status:**\ncode_executing\n**Action:**\n```python\n# Read the file and check its columns and data types\nimport pandas as pd\ndata = pd.read_csv('employee_data.csv')\ndata.info()\n```\n\n**Observation:**: The return information after executing the above code is <class 'pandas.core.frame.DataFrame'>\nRangeIndex: 1000 entries, 0 to 999\nData columns (total 5 columns):\n #   Column      Non-Null Count  Dtype \n---  ------      --------------  ----- \n 0   Name        1000 non-null   object\n 1   Position    1000 non-null   object\n 2   Join Date   1000 non-null   object\n 3   Salary      1000 non-null   int64 \n 4   Department  1000 non-null   object\ndtypes: int64(1), object(4)\nmemory usage: 39.2+ KB\n.\n\n\n\n**Thoughts:**\nThe file \"employee_data.csv\" exists and contains 5 columns with different data types. Now, we need to create a bar chart.\n**Action Status:**\ncode_executing\n**Action:**\n```python\n# Create a bar chart\nimport matplotlib.pyplot as plt\n\n# Count the number of employees in each department\ndepartment_counts = data['Department'].value_counts()\n\n# Plot the bar chart\ndepartment_counts.plot(kind='bar')\nplt.title('Number of Employees in Each Department')\nplt.xlabel('Department')\nplt.ylabel('Number of Employees')\nplt.show()\n```\n\n**Observation:**: The return figure name is 15106089-fd82-11ee-915c-845cf3ef83a9 after executing the above code.\n",
      "parsed_output": {
        "Thoughts": "The file \"employee_data.csv\" exists and contains 5 columns with different data types. Now, we need to create a bar chart.",
        "Action Status": "code_executing",
        "Action": "```python\n# Create a bar chart\nimport matplotlib.pyplot as plt\n\n# Count the number of employees in each department\ndepartment_counts = data['Department'].value_counts()\n\n# Plot the bar chart\ndepartment_counts.plot(kind='bar')\nplt.title('Number of Employees in Each Department')\nplt.xlabel('Department')\nplt.ylabel('Number of Employees')\nplt.show()\n```"
      },
      "spec_parsed_output": {
        "Thoughts": "The file \"employee_data.csv\" exists and contains 5 columns with different data types. Now, we need to create a bar chart.",
        "Action Status": "code_executing",
        "Action": "# Create a bar chart\nimport matplotlib.pyplot as plt\n\n# Count the number of employees in each department\ndepartment_counts = data['Department'].value_counts()\n\n# Plot the bar chart\ndepartment_counts.plot(kind='bar')\nplt.title('Number of Employees in Each Department')\nplt.xlabel('Department')\nplt.ylabel('Number of Employees')\nplt.show()",
        "code": "# Create a bar chart\nimport matplotlib.pyplot as plt\n\n# Count the number of employees in each department\ndepartment_counts = data['Department'].value_counts()\n\n# Plot the bar chart\ndepartment_counts.plot(kind='bar')\nplt.title('Number of Employees in Each Department')\nplt.xlabel('Department')\nplt.ylabel('Number of Employees')\nplt.show()"
      },
      "parsed_output_list": [
        {
          "Thoughts": "The user needs to confirm the existence of the \"employee_data.csv\" file, check its columns and data types, and then create a bar chart.",
          "Action Status": "code_executing",
          "Action": "```python\n# Check if the file \"employee_data.csv\" exists\nimport os\nfile_exists = os.path.isfile('employee_data.csv')\nfile_exists\n```"
        },
        {
          "Observation": "The return information after executing the above code is True\n.\n\n"
        },
        {
          "Thoughts": "The file \"employee_data.csv\" exists, so now we need to check its columns and data types.",
          "Action Status": "code_executing",
          "Action": "```python\n# Read the file and check its columns and data types\nimport pandas as pd\ndata = pd.read_csv('employee_data.csv')\ndata.info()\n```"
        },
        {
          "Observation": "The return information after executing the above code is <class 'pandas.core.frame.DataFrame'>\nRangeIndex: 1000 entries, 0 to 999\nData columns (total 5 columns):\n #   Column      Non-Null Count  Dtype \n---  ------      --------------  ----- \n 0   Name        1000 non-null   object\n 1   Position    1000 non-null   object\n 2   Join Date   1000 non-null   object\n 3   Salary      1000 non-null   int64 \n 4   Department  1000 non-null   object\ndtypes: int64(1), object(4)\nmemory usage: 39.2+ KB\n.\n\n"
        },
        {
          "Thoughts": "The file \"employee_data.csv\" exists and contains 5 columns with different data types. Now, we need to create a bar chart.",
          "Action Status": "code_executing",
          "Action": "```python\n# Create a bar chart\nimport matplotlib.pyplot as plt\n\n# Count the number of employees in each department\ndepartment_counts = data['Department'].value_counts()\n\n# Plot the bar chart\ndepartment_counts.plot(kind='bar')\nplt.title('Number of Employees in Each Department')\nplt.xlabel('Department')\nplt.ylabel('Number of Employees')\nplt.show()\n```"
        },
        {
          "Observation": "The return figure name is 15106089-fd82-11ee-915c-845cf3ef83a9 after executing the above code.\n"
        }
      ],
      "task": null,
      "db_docs": [],
      "code_docs": [],
      "search_docs": [],
      "customed_kargs": {
        "code_content": "# Create a bar chart\nimport matplotlib.pyplot as plt\n\n# Count the number of employees in each department\ndepartment_counts = data['Department'].value_counts()\n\n# Plot the bar chart\ndepartment_counts.plot(kind='bar')\nplt.title('Number of Employees in Each Department')\nplt.xlabel('Department')\nplt.ylabel('Number of Employees')\nplt.show()",
        "tool_params": {}
      },
      "phase_name": null,
      "chain_name": null
    }
  ]
}