{
  "messages": [
    {
      "chat_index": "chain_test",
      "role_name": "user",
      "role_type": "user",
      "role_prompt": "",
      "input_query": "确认本地是否存在employee_data.csv，并查看它有哪些列和数据类型;然后画柱状图",
      "role_content": "确认本地是否存在employee_data.csv，并查看它有哪些列和数据类型;然后画柱状图",
      "step_content": "",
      "parsed_output": {},
      "spec_parsed_output": {},
      "parsed_output_list": [],
      "task": null,
      "db_docs": [],
      "code_docs": [],
      "search_docs": [],
      "customed_kargs": {
        "code_content": null,
        "tool_params": {}
      },
      "phase_name": null,
      "chain_name": null
    },
    {
      "chat_index": "chain_test",
      "role_name": "code_reacter",
      "role_type": "assistant",
      "role_prompt": "",
      "input_query": "确认本地是否存在employee_data.csv，并查看它有哪些列和数据类型;然后画柱状图",
      "role_content": "\n**Thoughts:** The code successfully creates a bar chart showing the distribution of employee salaries based on the data in the \"employee_data.csv\" file.\n\n**Action Status:** stopped\n\n**Action:** Response the final answer to the session records.\n\n## END!!!",
      "step_content": "\n\n**Thoughts:** The user needs to check if the file \"employee_data.csv\" exists locally, and then view its columns and data types. After that, they need to create a bar chart.\n\n**Action Status:** code_executing\n\n**Action:** \n```python\nimport pandas as pd\nimport os\n\n# Check if the file \"employee_data.csv\" exists locally\nfile_path = \"employee_data.csv\"\nfile_exists = os.path.exists(file_path)\n\n# If the file exists, read it and view its columns and data types\nif file_exists:\n    data = pd.read_csv(file_path)\n    print(data.dtypes)\n    # Create a bar chart\n    # Code for creating the bar chart will depend on the specific data and columns in the file\nelse:\n    print(\"File 'employee_data.csv' does not exist locally.\")\n```\n\n\n**Observation:**: The return information after executing the above code is Name          object\nPosition      object\nJoin Date     object\nSalary         int64\nDepartment    object\ndtype: object\n.\n\n\n\n**Thoughts:** \nThe code successfully checks if the file \"employee_data.csv\" exists locally and reads the data from it. Next, we need to create a bar chart based on the data in the file.\n\n**Action Status:** code_executing\n\n**Action:** \n```python\nimport matplotlib.pyplot as plt\n\n# Assuming we want to create a bar chart for the 'Salary' column\nplt.figure(figsize=(10, 6))\nplt.bar(data['Name'], data['Salary'])\nplt.xlabel('Employee Name')\nplt.ylabel('Salary')\nplt.title('Employee Salary Distribution')\nplt.xticks(rotation=45)\nplt.show()\n```\n\n\n**Observation:**: The return figure name is fdfd8640-fd82-11ee-89d7-845cf3ef83a9 after executing the above code.\n\n\n**Thoughts:** The code successfully creates a bar chart showing the distribution of employee salaries based on the data in the \"employee_data.csv\" file.\n\n**Action Status:** stopped\n\n**Action:** Response the final answer to the session records.\n\n## END!!!",
      "parsed_output": {
        "Thoughts": "The code successfully creates a bar chart showing the distribution of employee salaries based on the data in the \"employee_data.csv\" file.",
        "Action Status": "stopped",
        "Action": "Response the final answer to the session records.\n\n## END!!!"
      },
      "spec_parsed_output": {
        "Thoughts": "The code successfully creates a bar chart showing the distribution of employee salaries based on the data in the \"employee_data.csv\" file.",
        "Action Status": "stopped",
        "Action": "Response the final answer to the session records.\n\n## END!!!"
      },
      "parsed_output_list": [
        {
          "Thoughts": "The user needs to check if the file \"employee_data.csv\" exists locally, and then view its columns and data types. After that, they need to create a bar chart.",
          "Action Status": "code_executing",
          "Action": "```python\nimport pandas as pd\nimport os\n\n# Check if the file \"employee_data.csv\" exists locally\nfile_path = \"employee_data.csv\"\nfile_exists = os.path.exists(file_path)\n\n# If the file exists, read it and view its columns and data types\nif file_exists:\n    data = pd.read_csv(file_path)\n    print(data.dtypes)\n    # Create a bar chart\n    # Code for creating the bar chart will depend on the specific data and columns in the file\nelse:\n    print(\"File 'employee_data.csv' does not exist locally.\")\n```"
        },
        {
          "Observation": "The return information after executing the above code is Name          object\nPosition      object\nJoin Date     object\nSalary         int64\nDepartment    object\ndtype: object\n.\n\n"
        },
        {
          "Thoughts": "The code successfully checks if the file \"employee_data.csv\" exists locally and reads the data from it. Next, we need to create a bar chart based on the data in the file.",
          "Action Status": "code_executing",
          "Action": "```python\nimport matplotlib.pyplot as plt\n\n# Assuming we want to create a bar chart for the 'Salary' column\nplt.figure(figsize=(10, 6))\nplt.bar(data['Name'], data['Salary'])\nplt.xlabel('Employee Name')\nplt.ylabel('Salary')\nplt.title('Employee Salary Distribution')\nplt.xticks(rotation=45)\nplt.show()\n```"
        },
        {
          "Observation": "The return figure name is fdfd8640-fd82-11ee-89d7-845cf3ef83a9 after executing the above code.\n"
        },
        {
          "Thoughts": "The code successfully creates a bar chart showing the distribution of employee salaries based on the data in the \"employee_data.csv\" file.",
          "Action Status": "stopped",
          "Action": "Response the final answer to the session records.\n\n## END!!!"
        }
      ],
      "task": null,
      "db_docs": [],
      "code_docs": [],
      "search_docs": [],
      "customed_kargs": {
        "code_content": null,
        "tool_params": {}
      },
      "phase_name": null,
      "chain_name": null
    }
  ]
}